{"cameraMode":{"drawMode":0,"name":"Shaded","section":"Shading Mode"},"sceneLighting":true,"audioPlay":false,"sceneViewState":{"showFog":true,"showMaterialUpdate":false,"showSkybox":true,"showFlares":true,"showImageEffects":true,"showParticleSystems":true},"in2DMode":false,"pivot":{"x":23.350364685058595,"y":-1.4726123809814454,"z":-12.461297988891602},"rotation":{"x":-0.06156624108552933,"y":-0.5161674618721008,"z":0.03723517060279846,"w":-0.8534601926803589},"size":38.4859619140625,"orthographic":false}